{
  "persons": [
    {
      "name": "Ada Lovelace",
      "number": "39-44-5323523",
      "id": 2
    },
    {
      "name": "Dan Abramov",
      "number": "12-43-234345",
      "id": 3
    },
    {
      "name": "Mary Poppendieck",
      "number": "39-23-6423122",
      "id": 4
    },
    {
      "name": "Eashin Matubber",
      "number": "+358404141200",
      "id": 5
    },
    {
      "name": "oq",
      "number": 0,
      "id": 6
    },
    {
      "name": "q",
      "number": 0,
      "id": 7
    },
    {
      "name": "11",
      "number": 0,
      "id": 8
    },
    {
      "name": "test",
      "number": 0,
      "id": 9
    }
  ]
}